MANIFEST.in
setup.cfg
setup.py
jitter/__init__.py
jitter/cli.py
jitter.egg-info/PKG-INFO
jitter.egg-info/SOURCES.txt
jitter.egg-info/dependency_links.txt
jitter.egg-info/entry_points.txt
jitter.egg-info/requires.txt
jitter.egg-info/top_level.txt
jitter/android/__init__.py
jitter/android/create_pack.py
jitter/android/languages.json
jitter/android/plurals.json
jitter/android/process_pack.py
jitter/android/traverse.py