Metadata-Version: 1.1
Name: jitter
Version: 0.1.17
Summary: JITT Command Line Tool
Home-page: http://jitt.it
Author: Adam Kariv
Author-email: adam@everything.me
License: UNKNOWN
Download-URL: https://github.com/EverythingMe/jitter/tarball/0.1.17
Platform: UNKNOWN
